{
    "configurations": [
        {
            "name": "Win32",
            "includePath": [
                "${workspaceRoot}",
                "${workspaceRoot}/Core/Inc",
                "${workspaceRoot}/Drivers/STM32F4xx_HAL_Driver/Inc",
                "${workspaceRoot}/Drivers/CMSIS/Include",
                "${workspaceRoot}/Drivers/CMSIS/Device/ST/STM32F4xx/Include",
                "C:/Users/gabri/Documents/tools/gcc-arm-none-eabi-10.3-2021.10/arm-none-eabi/include",
                "C:/Users/gabri/Documents/tools/gcc-arm-none-eabi-10.3-2021.10/arm-none-eabi/include/c++/10.3.1",
                "C:/Users/gabri/Documents/tools/gcc-arm-none-eabi-10.3-2021.10/lib/gcc/arm-none-eabi/10.3.1/include",
                "C:/Users/gabri/Documents/tools/gcc-arm-none-eabi-10.3-2021.10/lib/gcc/arm-none-eabi/10.3.1/include-fixed",
                "C:/Users/gabri/Documents/tools/gcc-arm-none-eabi-10.3-2021.10/arm-none-eabi/include/machine",
                "C:/Users/gabri/Documents/tools/gcc-arm-none-eabi-10.3-2021.10/arm-none-eabi/include/newlib-nano",
                "C:/Users/gabri/Documents/tools/gcc-arm-none-eabi-10.3-2021.10/arm-none-eabi/include/sys"
            ],
            "defines": [
                "USE_HAL_DRIVER",
                "STM32F446xx",
                "_DEBUG",
                "UNICODE",
                "_UNICODE"
            ],
            "windowsSdkVersion": "10.0.19041.0",
            "compilerPath": "cl.exe",
            "cStandard": "c17",
            "cppStandard": "c++17",
            "intelliSenseMode": "windows-msvc-x64",
            "browse":
            {
                "path":
                [
                    "${workspaceRoot}",
                    "${workspaceRoot}/Core/Inc",
                    "${workspaceRoot}/Drivers/STM32F4xx_HAL_Driver/Inc",
                    "${workspaceRoot}/Drivers/CMSIS/Include",
                    "${workspaceRoot}/Drivers/CMSIS/Device/ST/STM32F4xx/Include",
                    "C:/Users/gabri/Documents/tools/gcc-arm-none-eabi-10.3-2021.10/arm-none-eabi/include",
                    "C:/Users/gabri/Documents/tools/gcc-arm-none-eabi-10.3-2021.10/arm-none-eabi/include/c++/10.3.1",
                    "C:/Users/gabri/Documents/tools/gcc-arm-none-eabi-10.3-2021.10/lib/gcc/arm-none-eabi/10.3.1/include",
                    "C:/Users/gabri/Documents/tools/gcc-arm-none-eabi-10.3-2021.10/lib/gcc/arm-none-eabi/10.3.1/include-fixed"
                ],
                 "limitSymbolsToIncludedHeaders": true,
                "databaseFilename": "${workspaceRoot}/.vscode/browse.vc.db"
            }
        }
    ],
    "version": 4
}